lightcurver/__init__.py
lightcurver/pipeline/__init__.py
lightcurver/pipeline/pipeline_dependency_graph.yaml
lightcurver/pipeline/state_checkers.py
lightcurver/pipeline/task_wrappers.py
lightcurver/pipeline/workflow_manager.py
lightcurver/pipeline/example_config_file/config.yaml
lightcurver/plotting/__init__.py
lightcurver/plotting/footprint_plotting.py
lightcurver/plotting/html_visualisation.py
lightcurver/plotting/image_plotting.py
lightcurver/plotting/joint_modelling_plotting.py
lightcurver/plotting/normalization_plotting.py
lightcurver/plotting/photometry_plotting.py
lightcurver/plotting/plot_curves_template.html
lightcurver/plotting/psf_plotting.py
lightcurver/plotting/sources_plotting.py
lightcurver/processes/__init__.py
lightcurver/processes/absolute_zeropoint_calculation.py
lightcurver/processes/alternate_plate_solving_adapt_existing_wcs.py
lightcurver/processes/alternate_plate_solving_with_gaia.py
lightcurver/processes/background_estimation.py
lightcurver/processes/cutout_making.py
lightcurver/processes/frame_characterization.py
lightcurver/processes/frame_importation.py
lightcurver/processes/frame_star_assignment.py
lightcurver/processes/normalization_calculation.py
lightcurver/processes/plate_solving.py
lightcurver/processes/psf_modelling.py
lightcurver/processes/roi_file_preparation.py
lightcurver/processes/roi_modelling.py
lightcurver/processes/star_extraction.py
lightcurver/processes/star_photometry.py
lightcurver/processes/star_querying.py
lightcurver/scripts/initialize.py
lightcurver/scripts/run.py
lightcurver/structure/__init__.py
lightcurver/structure/database.py
lightcurver/structure/exceptions.py
lightcurver/structure/user_config.py
lightcurver/structure/user_header_parser.py
lightcurver/utilities/__init__.py
lightcurver/utilities/absolute_magnitudes_from_gaia.py
lightcurver/utilities/absolute_magnitudes_from_panstarrs.py
lightcurver/utilities/chi2_selector.py
lightcurver/utilities/footprint.py
lightcurver/utilities/gaia.py
lightcurver-1.2.3.dist-info/LICENSE
lightcurver-1.2.3.dist-info/METADATA
lightcurver-1.2.3.dist-info/WHEEL
lightcurver-1.2.3.dist-info/entry_points.txt
lightcurver-1.2.3.dist-info/top_level.txt
lightcurver-1.2.3.dist-info/RECORD
