Metadata-Version: 2.2
Name: lightcurver
Version: 1.2.3
Summary: A thorough structure for precise photometry and forward modelling of time series of wide field images.
Author-email: Frédéric Dux <duxfrederic@gmail.com>
Project-URL: homepage, https://duxfrederic.github.io/lightcurver/
Project-URL: repository, https://github.com/duxfrederic/lightcurver
Keywords: photometry,astronomy,forward modelling,PSF,pipeline
License-File: LICENSE
Requires-Dist: pyyaml
Requires-Dist: matplotlib
Requires-Dist: astropy
Requires-Dist: numpy<2.0.0
Requires-Dist: sep
Requires-Dist: scipy
Requires-Dist: ephem
Requires-Dist: pandas
Requires-Dist: shapely
Requires-Dist: astroquery
Requires-Dist: h5py
Requires-Dist: astroscrappy
Requires-Dist: starred-astro>=1.4.7
Requires-Dist: pytest
Requires-Dist: numpy
Requires-Dist: scipy
Requires-Dist: h5py
Requires-Dist: photutils
Requires-Dist: astroalign
Requires-Dist: ruamel.yaml
Requires-Dist: widefield_plate_solver
Requires-Dist: ccdproc
Provides-Extra: test
Requires-Dist: pytest; extra == "test"
